{ 
    "data":
[
   {
      "32874" : "30763",
      "3080" : "3157",
      "mommy" : "Lotan",
      "155" : "155",
      "3465" : "3388",
      "dark" : "Dark",
      "legendary" : "Legendary"
   },
   {
      "32874" : "24429",
      "3080" : "3575",
      "mommy" : "Dracontium",
      "155" : "244",
      "3465" : "3377",
      "dark" : "Fire",
      "legendary" : "Legendary"
   },
   {
      "32874" : "29255",
      "3080" : "3377",
      "mommy" : "Nidaria",
      "155" : "155",
      "3465" : "3464",
      "dark" : "Water",
      "legendary" : "Legendary"
   },
   {
      "32874" : "31366",
      "3080" : "3531",
      "mommy" : "Hydrok The Forgotten",
      "155" : "244",
      "3465" : "3421",
      "dark" : "Water",
      "legendary" : "Legendary"
   },
   {
      "32874" : "22318",
      "3080" : "3465",
      "mommy" : "Commander Alvid",
      "155" : "305",
      "3465" : "3432",
      "dark" : "Fire",
      "legendary" : "Legendary"
   },
   {
      "32874" : "28651",
      "3080" : "3509",
      "mommy" : "Will Razor Face",
      "155" : "244",
      "3465" : "3454",
      "dark" : "Dark",
      "legendary" : "Legendary"
   },
   {
      "32874" : "22318",
      "3080" : "3575",
      "mommy" : "Tyros",
      "155" : "305",
      "3465" : "3399",
      "dark" : "Fire",
      "legendary" : "Legendary"
   },
   {
      "32874" : "27445",
      "3080" : "3377",
      "mommy" : "Vanoss",
      "155" : "305",
      "3465" : "3322",
      "dark" : "Thunder",
      "legendary" : "Legendary"
   },
   {
      "32874" : "31366",
      "3080" : "3267",
      "mommy" : "Gullin",
      "155" : "244",
      "3465" : "3388",
      "dark" : "Nature",
      "legendary" : "Legendary"
   },
   {
      "32874" : "23524",
      "3080" : "3542",
      "mommy" : "General Holter",
      "155" : "305",
      "3465" : "3421",
      "dark" : "Metal",
      "legendary" : "Legendary"
   },
   {
      "32874" : "30461",
      "3080" : "3157",
      "mommy" : "Eggeater",
      "155" : "244",
      "3465" : "3399",
      "dark" : "Magic",
      "legendary" : "Legendary"
   },
   {
      "32874" : "31969",
      "3080" : "3388",
      "mommy" : "The Ringer",
      "155" : "244",
      "3465" : "2805",
      "dark" : "Dark",
      "legendary" : "Legendary"
   },
   {
      "32874" : "25334",
      "3080" : "3465",
      "mommy" : "Tryon",
      "155" : "305",
      "3465" : "3278",
      "dark" : "Fire",
      "legendary" : "Legendary"
   },
   {
      "32874" : "29556",
      "3080" : "3542",
      "mommy" : "The Judgment",
      "155" : "244",
      "3465" : "3377",
      "dark" : "Nature",
      "legendary" : "Legendary"
   },
   {
      "32874" : "27143",
      "3080" : "3278",
      "mommy" : "Toy Master",
      "155" : "244",
      "3465" : "3465",
      "dark" : "Magic",
      "legendary" : "Legendary"
   },
   {
      "32874" : "24429",
      "3080" : "3388",
      "mommy" : "Blockheart",
      "155" : "244",
      "3465" : "3432",
      "dark" : "Magic",
      "legendary" : "Legendary"
   },
   {
      "32874" : "27445",
      "3080" : "3234",
      "mommy" : "Sarah",
      "155" : "244",
      "3465" : "3476",
      "dark" : "Nature",
      "legendary" : "Legendary"
   },
   {
      "32874" : "31667",
      "3080" : "3234",
      "mommy" : "The Prisoner",
      "155" : "244",
      "3465" : "2816",
      "dark" : "Water",
      "legendary" : "Legendary"
   },
   {
      "32874" : "28350",
      "3080" : "3531",
      "mommy" : "Anton Acorne",
      "155" : "244",
      "3465" : "3465",
      "dark" : "Water",
      "legendary" : "Legendary"
   },
   {
      "32874" : "26239",
      "3080" : "3509",
      "mommy" : "Uru",
      "155" : "305",
      "3465" : "3465",
      "dark" : "Magic",
      "legendary" : "Legendary"
   },
   {
      "32874" : "29255",
      "3080" : "3388",
      "mommy" : "ML-1 Yamato",
      "155" : "305",
      "3465" : "3399",
      "dark" : "Metal",
      "legendary" : "Legendary"
   },
   {
      "32874" : "31366",
      "3080" : "3531",
      "mommy" : "Scarr The Outcast",
      "155" : "305",
      "3465" : "3465",
      "dark" : "Magic",
      "legendary" : "Legendary"
   },
   {
      "32874" : "30461",
      "3080" : "3300",
      "mommy" : "General Alces",
      "155" : "305",
      "3465" : "3432",
      "dark" : "Nature",
      "legendary" : "Legendary"
   },
   {
      "32874" : "28350",
      "3080" : "3157",
      "mommy" : "Galante",
      "155" : "305",
      "3465" : "3476",
      "dark" : "Magic",
      "legendary" : "Legendary"
   },
   {
      "32874" : "31667",
      "3080" : "3245",
      "mommy" : "Darude",
      "155" : "305",
      "3465" : "3355",
      "dark" : "Earth",
      "legendary" : "Legendary"
   },
   {
      "32874" : "28651",
      "3080" : "3388",
      "mommy" : "Sphyyrnus",
      "155" : "244",
      "3465" : "3432",
      "dark" : "Water",
      "legendary" : "Legendary"
   },
   {
      "32874" : "27445",
      "3080" : "3553",
      "mommy" : "Malair",
      "155" : "305",
      "3465" : "3454",
      "dark" : "Magic",
      "legendary" : "Legendary"
   },
   {
      "32874" : "29255",
      "3080" : "3322",
      "mommy" : "Lux Aura",
      "155" : "244",
      "3465" : "3454",
      "dark" : "Light",
      "legendary" : "Legendary"
   },
   {
      "32874" : "33779",
      "3080" : "2926",
      "mommy" : "Lostyghost",
      "155" : "244",
      "3465" : "3542",
      "dark" : "Dark",
      "legendary" : "Legendary"
   },
   {
      "32874" : "31668",
      "3080" : "2464",
      "mommy" : "Panda Claus",
      "155" : "244",
      "3465" : "3542",
      "dark" : "Magic",
      "legendary" : "Legendary"
   },
   {
      "32874" : "25334",
      "3080" : "2310",
      "mommy" : "Cupid",
      "155" : "305",
      "3465" : "3542",
      "dark" : "Magic",
      "legendary" : "Legendary"
   },
   {
      "32874" : "28651",
      "3080" : "3124",
      "mommy" : "Krampus",
      "155" : "244",
      "3465" : "3531",
      "dark" : "Dark",
      "legendary" : "Legendary"
   },
   {
      "32874" : "21112",
      "3080" : "2926",
      "mommy" : "Thorder",
      "155" : "305",
      "3465" : "3509",
      "dark" : "Thunder",
      "legendary" : "Legendary"
   },
   {
      "32874" : "27143",
      "3080" : "3223",
      "mommy" : "Queen Luthien",
      "155" : "244",
      "3465" : "3476",
      "dark" : "Light",
      "legendary" : "Legendary"
   },
   {
      "32874" : "29556",
      "3080" : "3047",
      "mommy" : "Laomu",
      "155" : "305",
      "3465" : "3476",
      "dark" : "Nature",
      "legendary" : "Legendary"
   },
   {
      "32874" : "26540",
      "3080" : "3322",
      "mommy" : "R.O.F.L",
      "155" : "305",
      "3465" : "3476",
      "dark" : "Thunder",
      "legendary" : "Legendary"
   },
   {
      "32874" : "22318",
      "3080" : "3509",
      "mommy" : "Klectus",
      "155" : "244",
      "3465" : "3465",
      "dark" : "Dark",
      "legendary" : "Legendary"
   },
   {
      "32874" : "25635",
      "3080" : "3146",
      "mommy" : "Lilysha",
      "155" : "244",
      "3465" : "3465",
      "dark" : "Dark",
      "legendary" : "Legendary"
   },
   {
      "32874" : "27144",
      "3080" : "3300",
      "mommy" : "Noctum",
      "155" : "244",
      "3465" : "3465",
      "dark" : "Dark",
      "legendary" : "Legendary"
   },
   {
      "32874" : "28651",
      "3080" : "3146",
      "mommy" : "Caillech",
      "155" : "244",
      "3465" : "3465",
      "dark" : "Water",
      "legendary" : "Legendary"
   },
   {
      "32874" : "27747",
      "3080" : "3509",
      "mommy" : "General Darmith",
      "155" : "305",
      "3465" : "3465",
      "dark" : "Fire",
      "legendary" : "Legendary"
   },
   {
      "32874" : "27747",
      "3080" : "3575",
      "mommy" : "Annihilator R2",
      "155" : "305",
      "3465" : "3465",
      "dark" : "Metal",
      "legendary" : "Legendary"
   },
   {
      "32874" : "24429",
      "3080" : "3355",
      "mommy" : "VoltaiK",
      "155" : "305",
      "3465" : "3465",
      "dark" : "Thunder",
      "legendary" : "Legendary"
   },
   {
      "32874" : "29255",
      "3080" : "3267",
      "mommy" : "Oghma",
      "155" : "244",
      "3465" : "3454",
      "dark" : "Light",
      "legendary" : "Legendary"
   },
   {
      "32874" : "28651",
      "3080" : "3080",
      "mommy" : "Cavenfish",
      "155" : "244",
      "3465" : "3454",
      "dark" : "Water",
      "legendary" : "Legendary"
   },
   {
      "32874" : "28651",
      "3080" : "3399",
      "mommy" : "Raccoon",
      "155" : "305",
      "3465" : "3454",
      "dark" : "Fire",
      "legendary" : "Legendary"
   },
   {
      "32874" : "28651",
      "3080" : "3311",
      "mommy" : "Greedy Dragon",
      "155" : "305",
      "3465" : "3454",
      "dark" : "Fire",
      "legendary" : "Legendary"
   },
   {
      "32874" : "25334",
      "3080" : "3454",
      "mommy" : "General Shannara",
      "155" : "305",
      "3465" : "3454",
      "dark" : "Magic",
      "legendary" : "Legendary"
   },
   {
      "32874" : "28652",
      "3080" : "3322",
      "mommy" : "Ultrabot",
      "155" : "305",
      "3465" : "3454",
      "dark" : "Metal",
      "legendary" : "Legendary"
   },
   {
      "32874" : "29858",
      "3080" : "3553",
      "mommy" : "Killeraptor",
      "155" : "305",
      "3465" : "3432",
      "dark" : "Earth",
      "legendary" : "Legendary"
   },
   {
      "32874" : "29255",
      "3080" : "3311",
      "mommy" : "White Pandalf",
      "155" : "305",
      "3465" : "3432",
      "dark" : "Magic",
      "legendary" : "Legendary"
   },
   {
      "32874" : "29858",
      "3080" : "3454",
      "mommy" : "General Uria",
      "155" : "305",
      "3465" : "3432",
      "dark" : "Thunder",
      "legendary" : "Legendary"
   },
   {
      "32874" : "30461",
      "3080" : "3157",
      "mommy" : "Dr. Hazard",
      "155" : "244",
      "3465" : "3421",
      "dark" : "Dark",
      "legendary" : "Legendary"
   },
   {
      "32874" : "30461",
      "3080" : "3355",
      "mommy" : "Master Skeel",
      "155" : "244",
      "3465" : "3421",
      "dark" : "Dark",
      "legendary" : "Legendary"
   },
   {
      "32874" : "26239",
      "3080" : "3311",
      "mommy" : "Mmonster",
      "155" : "244",
      "3465" : "3421",
      "dark" : "Dark",
      "legendary" : "Legendary"
   },
   {
      "32874" : "26540",
      "3080" : "3278",
      "mommy" : "General Thetys",
      "155" : "244",
      "3465" : "3421",
      "dark" : "Water",
      "legendary" : "Legendary"
   },
   {
      "32874" : "30763",
      "3080" : "3432",
      "mommy" : "Qin",
      "155" : "305",
      "3465" : "3421",
      "dark" : "Earth",
      "legendary" : "Legendary"
   },
   {
      "32874" : "29255",
      "3080" : "3278",
      "mommy" : "Pixelion",
      "155" : "305",
      "3465" : "3421",
      "dark" : "Magic",
      "legendary" : "Legendary"
   },
   {
      "32874" : "26540",
      "3080" : "3157",
      "mommy" : "Reptie",
      "155" : "305",
      "3465" : "3421",
      "dark" : "Magic",
      "legendary" : "Legendary"
   },
   {
      "32874" : "31366",
      "3080" : "3542",
      "mommy" : "Drazz",
      "155" : "305",
      "3465" : "3421",
      "dark" : "Metal",
      "legendary" : "Legendary"
   },
   {
      "32874" : "31366",
      "3080" : "3542",
      "mommy" : "Metalhead",
      "155" : "305",
      "3465" : "3421",
      "dark" : "Metal",
      "legendary" : "Legendary"
   },
   {
      "32874" : "29556",
      "3080" : "3300",
      "mommy" : "Akhenotep",
      "155" : "244",
      "3465" : "3399",
      "dark" : "Dark",
      "legendary" : "Legendary"
   },
   {
      "32874" : "29556",
      "3080" : "3344",
      "mommy" : "Count Vlad",
      "155" : "244",
      "3465" : "3399",
      "dark" : "Dark",
      "legendary" : "Legendary"
   },
   {
      "32874" : "27747",
      "3080" : "3454",
      "mommy" : "King Daeron",
      "155" : "244",
      "3465" : "3399",
      "dark" : "Light",
      "legendary" : "Legendary"
   },
   {
      "32874" : "28652",
      "3080" : "3311",
      "mommy" : "Varuna",
      "155" : "244",
      "3465" : "3399",
      "dark" : "Water",
      "legendary" : "Legendary"
   },
   {
      "32874" : "31969",
      "3080" : "3454",
      "mommy" : "General Atum",
      "155" : "305",
      "3465" : "3399",
      "dark" : "Earth",
      "legendary" : "Legendary"
   },
   {
      "32874" : "26239",
      "3080" : "3575",
      "mommy" : "Megaosteum",
      "155" : "305",
      "3465" : "3399",
      "dark" : "Fire",
      "legendary" : "Legendary"
   },
   {
      "32874" : "28350",
      "3080" : "3467",
      "mommy" : "Barbatos",
      "155" : "244",
      "3465" : "3388",
      "dark" : "Dark",
      "legendary" : "Legendary"
   },
   {
      "32874" : "29556",
      "3080" : "2772",
      "mommy" : "Nemestrinus",
      "155" : "244",
      "3465" : "3388",
      "dark" : "Nature",
      "legendary" : "Legendary"
   },
   {
      "32874" : "26540",
      "3080" : "2926",
      "mommy" : "Lord Atlantis",
      "155" : "244",
      "3465" : "3388",
      "dark" : "Water",
      "legendary" : "Legendary"
   },
   {
      "32874" : "27143",
      "3080" : "3542",
      "mommy" : "Deadwolf",
      "155" : "305",
      "3465" : "3388",
      "dark" : "Earth",
      "legendary" : "Legendary"
   },
   {
      "32874" : "32572",
      "3080" : "3509",
      "mommy" : "Monster Clutch",
      "155" : "305",
      "3465" : "3388",
      "dark" : "Magic",
      "legendary" : "Legendary"
   },
   {
      "32874" : "26239",
      "3080" : "2310",
      "mommy" : "Timerion",
      "155" : "305",
      "3465" : "3388",
      "dark" : "Metal",
      "legendary" : "Legendary"
   },
   {
      "32874" : "22016",
      "3080" : "3003",
      "mommy" : "Thundhare",
      "155" : "305",
      "3465" : "3388",
      "dark" : "Thunder",
      "legendary" : "Legendary"
   },
   {
      "32874" : "31366",
      "3080" : "3388",
      "mommy" : "Minotaurus",
      "155" : "305",
      "3465" : "3377",
      "dark" : "Earth",
      "legendary" : "Legendary"
   },
   {
      "32874" : "27143",
      "3080" : "3509",
      "mommy" : "Megapolaris",
      "155" : "305",
      "3465" : "3377",
      "dark" : "Metal",
      "legendary" : "Legendary"
   },
   {
      "32874" : "29652",
      "3080" : "3531",
      "mommy" : "Exo Skeel",
      "155" : "305",
      "3465" : "3377",
      "dark" : "Thunder",
      "legendary" : "Legendary"
   },
   {
      "32874" : "30763",
      "3080" : "3278",
      "mommy" : "Basthet",
      "155" : "305",
      "3465" : "3355",
      "dark" : "Earth",
      "legendary" : "Legendary"
   },
   {
      "32874" : "30763",
      "3080" : "3465",
      "mommy" : "Ralbog",
      "155" : "305",
      "3465" : "3344",
      "dark" : "Fire",
      "legendary" : "Legendary"
   },
   {
      "32874" : "31969",
      "3080" : "3498",
      "mommy" : "Layth",
      "155" : "244",
      "3465" : "3311",
      "dark" : "Light",
      "legendary" : "Legendary"
   },
   {
      "32874" : "31366",
      "3080" : "3234",
      "mommy" : "General Ingvar",
      "155" : "244",
      "3465" : "3267",
      "dark" : "Light",
      "legendary" : "Legendary"
   },
   {
      "32874" : "29858",
      "3080" : "3465",
      "mommy" : "Cyan",
      "155" : "305",
      "3465" : "3267",
      "dark" : "Nature",
      "legendary" : "Legendary"
   },
   {
      "32874" : "31366",
      "3080" : "3047",
      "mommy" : "Uriel",
      "155" : "244",
      "3465" : "3245",
      "dark" : "Light",
      "legendary" : "Legendary"
   },
   {
      "32874" : "31969",
      "3080" : "3201",
      "mommy" : "Flirty",
      "155" : "305",
      "3465" : "3245",
      "dark" : "Nature",
      "legendary" : "Legendary"
   },
   {
      "32874" : "19000",
      "3080" : "3311",
      "mommy" : "Darkzgul",
      "155" : "244",
      "3465" : "3234",
      "dark" : "Dark",
      "legendary" : "Legendary"
   },
   {
      "32874" : "25032",
      "3080" : "2772",
      "mommy" : "Nebotus",
      "155" : "244",
      "3465" : "3234",
      "dark" : "Dark",
      "legendary" : "Legendary"
   },
   {
      "32874" : "28651",
      "3080" : "3300",
      "mommy" : "Chocolove",
      "155" : "305",
      "3465" : "3234",
      "dark" : "Magic",
      "legendary" : "Legendary"
   },
   {
      "32874" : "25636",
      "3080" : "3388",
      "mommy" : "Son-Cookie",
      "155" : "305",
      "3465" : "3157",
      "dark" : "Magic",
      "legendary" : "Legendary"
   },
   {
      "32874" : "26540",
      "3080" : "3322",
      "mommy" : "CYMO",
      "155" : "305",
      "3465" : "3157",
      "dark" : "Thunder",
      "legendary" : "Legendary"
   },
   {
      "32874" : "29255",
      "3080" : "2761",
      "mommy" : "Firelequin",
      "155" : "305",
      "3465" : "3124",
      "dark" : "Fire",
      "legendary" : "Legendary"
   },
   {
      "32874" : "31667",
      "3080" : "3465",
      "mommy" : "Lord Mammoth",
      "155" : "244",
      "3465" : "3091",
      "dark" : "Water",
      "legendary" : "Legendary"
   },
   {
      "32874" : "28652",
      "3080" : "3575",
      "mommy" : "The Firestorm",
      "155" : "305",
      "3465" : "3091",
      "dark" : "Fire",
      "legendary" : "Legendary"
   },
   {
      "32874" : "22016",
      "3080" : "3234",
      "mommy" : "Sir Slumberly",
      "155" : "244",
      "3465" : "3080",
      "dark" : "Dark",
      "legendary" : "Legendary"
   },
   {
      "32874" : "23524",
      "3080" : "3080",
      "mommy" : "Arch Knight",
      "155" : "244",
      "3465" : "3080",
      "dark" : "Light",
      "legendary" : "Legendary"
   },
   {
      "32874" : "32572",
      "3080" : "2464",
      "mommy" : "Goldfield",
      "155" : "244",
      "3465" : "3080",
      "dark" : "Magic",
      "legendary" : "Legendary"
   },
   {
      "32874" : "23524",
      "3080" : "3080",
      "mommy" : "White Walker",
      "155" : "244",
      "3465" : "3080",
      "dark" : "Water",
      "legendary" : "Legendary"
   },
   {
      "32874" : "25334",
      "3080" : "3322",
      "mommy" : "Lord Moltus",
      "155" : "305",
      "3465" : "3080",
      "dark" : "Fire",
      "legendary" : "Legendary"
   },
   {
      "32874" : "29255",
      "3080" : "2937",
      "mommy" : "Roastie",
      "155" : "305",
      "3465" : "3080",
      "dark" : "Nature",
      "legendary" : "Legendary"
   },
   {
      "32874" : "25032",
      "3080" : "3311",
      "mommy" : "Vadamagma",
      "155" : "305",
      "3465" : "3003",
      "dark" : "Fire",
      "legendary" : "Legendary"
   },
   {
      "32874" : "29858",
      "3080" : "2970",
      "mommy" : "Firus",
      "155" : "244",
      "3465" : "2926",
      "dark" : "Nature",
      "legendary" : "Legendary"
   },
   {
      "32874" : "27445",
      "3080" : "2926",
      "mommy" : "Shi Hou",
      "155" : "305",
      "3465" : "2926",
      "dark" : "Earth",
      "legendary" : "Legendary"
   },
   {
      "32874" : "27144",
      "3080" : "2937",
      "mommy" : "Lagerchaun",
      "155" : "244",
      "3465" : "2783",
      "dark" : "Nature",
      "legendary" : "Legendary"
   },
   {
      "32874" : "40112",
      "3080" : "3498",
      "mommy" : "Ouros",
      "155" : "305",
      "3465" : "2772",
      "dark" : "Earth",
      "legendary" : "Legendary"
   },
   {
      "32874" : "32572",
      "3080" : "3311",
      "mommy" : "Rockantium",
      "155" : "305",
      "3465" : "2464",
      "dark" : "Earth",
      "legendary" : "Legendary"
   },
   {
      "32874" : "26540",
      "3080" : "3619",
      "mommy" : "Worker Hulk",
      "155" : "244",
      "3465" : "2156",
      "dark" : "Magic",
      "legendary" : "Legendary"
   }
]
}
